openai_pricing_logger/__init__.py
openai_pricing_logger/logger.py
openai_pricing_logger/pricing.json
openai_pricing_logger-0.0.2.dist-info/LICENSE
openai_pricing_logger-0.0.2.dist-info/METADATA
openai_pricing_logger-0.0.2.dist-info/WHEEL
openai_pricing_logger-0.0.2.dist-info/top_level.txt
openai_pricing_logger-0.0.2.dist-info/RECORD
