Metadata-Version: 2.1
Name: openai-pricing-logger
Version: 0.0.2
Summary: A package to log OpenAI API costs
Home-page: https://github.com/yachty66/openai_pricing_logger
Author: Max Hager
Author-email: maxhager28@gmail.com
Classifier: Development Status :: 3 - Alpha
Classifier: Intended Audience :: Developers
Classifier: License :: OSI Approved :: MIT License
Classifier: Programming Language :: Python :: 3
Classifier: Programming Language :: Python :: 3.6
Classifier: Programming Language :: Python :: 3.7
Classifier: Programming Language :: Python :: 3.8
Classifier: Programming Language :: Python :: 3.9
Requires-Python: >=3.6
License-File: LICENSE
